Step 2/hockey.v
module hockey(

    input clk,
    input rst,
    
    input BTN_A,
    input BTN_B,
    
    input [1:0] DIR_A,
    input [1:0] DIR_B,
    
    input [2:0] Y_in_A,
    input [2:0] Y_in_B,
   
    /*
    output reg LEDA,
    output reg LEDB,
    output reg [4:0] LEDX,
    
    output reg [6:0] SSD7,
    output reg [6:0] SSD6,
    output reg [6:0] SSD5,
    output reg [6:0] SSD4, 
    output reg [6:0] SSD3,
    output reg [6:0] SSD2,
    output reg [6:0] SSD1,
    output reg [6:0] SSD0   
    */
	
	output reg [2:0] X_COORD,
	output reg [2:0] Y_COORD
	
    );

    reg [7:0]timer; //max deger 199 olcak 2^8
    reg [2:0]scoreA;
    reg [2:0]scoreB;
    reg [1:0]lastTurn;
    reg turn;
    reg [1:0]dir;

    //List of states
    localparam IDLE = 4'd0;
    localparam DISPLAY = 4'd1;
    localparam HIT_A = 4'd2;
    localparam HIT_B = 4'd3;
    localparam SEND_A = 4'd4;
    localparam SEND_B = 4'd5;
    localparam RESP_A = 4'd6;
    localparam RESP_B = 4'd7;
    localparam GOAL_A = 4'd8;
    localparam GOAL_B = 4'd9;
    localparam GAMEOVER = 4'd10;

    reg [4:0] currentstate;
    
    always @(posedge clk or posedge rst)
    begin
        if(rst) begin
            X_COORD<=3'b000;
            Y_COORD<=3'b000;
            timer<=0;
            scoreA<=0;
            scoreB<=0;
            lastTurn<=0;
            currentstate <= IDLE;
        end
        else if(currentstate != GAMEOVER)begin
        
            case(currentstate)

                IDLE:begin

                    if((BTN_A || BTN_B))begin

                        if(BTN_A)begin
                            turn<=0;
                            currentstate <= DISPLAY;
                        end
                        else if(BTN_B)begin
                            turn<=1;
                            currentstate <= DISPLAY;
                        end
        
                    end
                
                end

                DISPLAY:begin

                    if(timer<199)begin
                        timer<=timer+1;
                    end
                    else begin
                        timer<=0;
                        if(turn == 1)begin
                            currentstate <= HIT_B;
                        end
                        else begin
                            currentstate <= HIT_A;
                        end
                    end
        
                end

                //MIRROR STARTS HERE

                HIT_B:begin

                    if(BTN_B && Y_in_B < 5)begin
                        X_COORD <= 4;
                        Y_COORD <= Y_in_B;
                        dir <= DIR_B;
                        currentstate <= SEND_A;
                    end
                    else begin
                        currentstate <= HIT_B;
                    end
                    
                end

                SEND_A:begin

                    if(timer<199)begin
                        timer<=timer+1;
                    end
                    else begin
                        timer<=0;

                        case(dir)

                            2'b10:begin

                                if(Y_COORD == 0)begin
                                    dir <= 2'b01;
                                    Y_COORD <= Y_COORD + 1;                                   
                                end
                                else begin
                                    Y_COORD <= Y_COORD - 1;
                                end
                            
                            end

                            2'b01:begin

                                if(Y_COORD == 4)begin
                                    dir <= 2'b10;
                                    Y_COORD <= Y_COORD - 1;                                   
                                end
                                else begin
                                    Y_COORD <= Y_COORD + 1;
                                end

                            end

                            2'b00:begin
                            
                            end

                        endcase

                        if(X_COORD > 1)begin
                            X_COORD <= X_COORD - 1;
                            currentstate <= SEND_A;
                        end
                        else begin
                            X_COORD <= 0;
                            currentstate <= RESP_A;
                        end

                    end
                    
                end

                RESP_A:begin

                    if(timer<199)begin

                        if(BTN_A && (Y_COORD == Y_in_A))begin
                            X_COORD <= 1;
                            timer <= 0;

                            case(dir)

                                2'b10:begin

                                    if(Y_COORD == 0)begin
                                        dir <= 2'b01;
                                        Y_COORD <= Y_COORD + 1;  
                                        currentstate <= SEND_B;                                 
                                    end
                                    else begin
                                        dir <= DIR_A;
                                        Y_COORD <= Y_COORD - 1;
                                        currentstate <= SEND_B;
                                    end
                                
                                end

                                2'b01:begin

                                    if(Y_COORD == 4)begin
                                        dir <= 2'b10;
                                        Y_COORD <= Y_COORD - 1;  
                                        currentstate <= SEND_B;                                 
                                    end
                                    else begin
                                        dir <= DIR_A;
                                        Y_COORD <= Y_COORD + 1;
                                        currentstate <= SEND_B;
                                    end

                                end

                                2'b00:begin

                                    dir <= DIR_B;
                                    currentstate <= SEND_B;
                                
                                end

                            endcase

                        end
                        else begin
                            timer <= timer + 1;
                        end
                    end
                    else begin
                        timer<=0;
                        scoreB <= scoreB + 1;
                        currentstate <= GOAL_B;
                    end
                end

                GOAL_B:begin

                    if(timer<199)begin
                        timer<=timer+1;
                    end
                    else begin
                        timer<=0;
                        if(scoreB == 3)begin
                            turn <= 1;
                            currentstate <= GAMEOVER;
                        end
                        else begin
                            currentstate <= HIT_A;
                        end
                    end
                end

                //MIRROR ENDS HERE

                //START OF THE COPIED CODE

                HIT_A:begin

                    if(BTN_A && Y_in_A < 5)begin
                        X_COORD <= 0;
                        Y_COORD <= Y_in_A;
                        dir <= DIR_A;
                        currentstate <= SEND_B;
                    end
                    else begin
                        currentstate <= HIT_A;
                    end
                    
                end

                SEND_B:begin

                    if(timer<199)begin
                        timer<=timer+1;
                    end
                    else begin
                        timer<=0;

                        case(dir)

                            2'b10:begin

                                if(Y_COORD == 0)begin
                                    dir <= 2'b01;
                                    Y_COORD <= Y_COORD + 1;                                   
                                end
                                else begin
                                    Y_COORD <= Y_COORD - 1;
                                end
                            
                            end

                            2'b01:begin

                                if(Y_COORD == 4)begin
                                    dir <= 2'b10;
                                    Y_COORD <= Y_COORD - 1;                                   
                                end
                                else begin
                                    Y_COORD <= Y_COORD + 1;
                                end

                            end

                            2'b00:begin
                            
                            end

                        endcase

                        if(X_COORD < 3)begin
                            X_COORD <= X_COORD + 1;
                            currentstate <= SEND_B;
                        end
                        else begin
                            X_COORD <= 4;
                            currentstate <= RESP_B;
                        end

                    end
                    
                end

                RESP_B:begin

                    if(timer<199)begin

                        if(BTN_B && (Y_COORD == Y_in_B))begin
                            X_COORD <= 3;
                            timer <= 0;

                            case(dir)

                                2'b10:begin

                                    if(Y_COORD == 0)begin
                                        dir <= 2'b01;
                                        Y_COORD <= Y_COORD + 1;  
                                        currentstate <= SEND_A;                                 
                                    end
                                    else begin
                                        dir <= DIR_B;
                                        Y_COORD <= Y_COORD - 1;
                                        currentstate <= SEND_A;
                                    end
                                
                                end

                                2'b01:begin

                                    if(Y_COORD == 4)begin
                                        dir <= 2'b10;
                                        Y_COORD <= Y_COORD - 1;  
                                        currentstate <= SEND_A;                                 
                                    end
                                    else begin
                                        dir <= DIR_B;
                                        Y_COORD <= Y_COORD + 1;
                                        currentstate <= SEND_A;
                                    end

                                end

                                2'b00:begin

                                    dir <= DIR_A;
                                    currentstate <= SEND_A;
                                
                                end

                            endcase

                        end
                        else begin
                            timer <= timer + 1;
                        end
                    end
                    else begin
                        timer<=0;
                        scoreA <= scoreA + 1;
                        currentstate <= GOAL_A;
                    end
                end

                GOAL_A:begin

                    if(timer<199)begin
                        timer<=timer+1;
                    end
                    else begin
                        timer<=0;
                        if(scoreA == 3)begin
                            turn <= 1;
                            currentstate <= GAMEOVER;
                        end
                        else begin
                            currentstate <= HIT_B;
                        end
                    end
                end

                //END OF THE COPIED CODE
                
            endcase
  
        end
    end

endmodule

Step 2/hockey_tb.v
module hockey_tb();


parameter HP = 5;       // Half period of our clock signal
parameter FP = (2*HP);  // Full period of our clock signal

reg clk, rst, BTN_A, BTN_B;
reg [1:0] DIR_A;
reg [1:0] DIR_B;
reg [2:0] Y_in_A;
reg [2:0] Y_in_B;

wire [2:0] X_COORD, Y_COORD;

// Our design-under-test is the DigiHockey module
hockey dut(clk, rst, BTN_A, BTN_B, DIR_A, DIR_B, Y_in_A, Y_in_B, X_COORD,Y_COORD);

// This always statement automatically cycles between clock high and clock low in HP (Half Period) time. Makes writing test-benches easier.
always #HP clk = ~clk;

initial begin

    $dumpfile("hockey.vcd"); // Our waveform is saved under this file.
    $dumpvars(0,hockey_tb); // * Get the variables from the module.

    $display("Simulation started.");

    clk = 0; 
    rst = 0;
    BTN_A = 0;
    BTN_B = 0;
    DIR_A = 0;
    DIR_B = 0;
    Y_in_A = 0;
    Y_in_B = 0;

    rst=1;
    #(200 * FP);
    rst=0;

    // Here, you are asked to write your test scenario.

    //A starts

    BTN_A=1;
    #(200 * FP);
    BTN_A=0;
    #(200 * FP);

    //A hits
    DIR_A=0;
    Y_in_A=3;
    BTN_A=1;
    #(200 * FP);
    BTN_A=0;

    //Puck moves
    #(600 * FP);

    DIR_B=2;
    Y_in_B=2; //B missses
    BTN_B=1;
    #(200 * FP);
    BTN_B=0;

    //A scores

    #(200 * FP);

    //B starts
    DIR_B=1;
    Y_in_B=1; 
    BTN_B=1;
    #(200 * FP);
    BTN_B=0;

    //Puck moves
    #(800 * FP);

    DIR_A=0;
    Y_in_A=3; //A hits
    BTN_A=1;
    #(200 * FP);
    BTN_A=0;

    //Puck moves
    #(500 * FP);

    DIR_B=2;
    Y_in_B=2; //B hits
    BTN_B=1;
    #(200 * FP);
    BTN_B=0;

    //Puck moves
    #(500 * FP);

    DIR_A=1;
    Y_in_A=0; //A misses
    BTN_A=1;
    #(200 * FP);
    BTN_A=0;

    //B scores

    #(200 * FP);
    
    //A starts

    DIR_A=1;
    Y_in_A=1; 
    BTN_A=1;
    #(200 * FP);
    BTN_A=0;

    //Puck moves
    #(600 * FP);

    DIR_B=0;
    Y_in_B=1; //B misses
    BTN_B=1;
    #(200 * FP);
    BTN_B=0;

    //A scores

    #(200 * FP);

    //B starts

    DIR_B=1;
    Y_in_B=2; 
    BTN_B=1;

    #(200 * FP);
    BTN_B=0;

    //Puck moves
    #(800 * FP);

    DIR_A=2;
    Y_in_A=2; //A hits
    BTN_A=1;

    #(200 * FP);
    BTN_A=0;

    //Puck moves
    #(500 * FP);

    DIR_B=2;
    Y_in_B=2; //B hits
    BTN_B=1;

    #(200 * FP);
    BTN_B=0;
    
    //Puck moves
    #(500 * FP);

    DIR_A=1;
    Y_in_A=0; //A hits
    BTN_A=1;

    #(200 * FP);
    BTN_A=0;

    //Puck moves
    #(500 * FP);

    DIR_B=1;
    Y_in_B=1; //B misses
    BTN_B=1;
    #(200 * FP);
    BTN_B=0;

    //A scores

    #(200 * FP);
    
    #(200 * FP);

    //Game over

    //Try giving inputs despite game ending (it will not work)

    DIR_B=1;
    Y_in_B=2; 
    BTN_B=1;
    #(200 * FP);
    BTN_B=0;

    #(200 * FP);

    $display("Simulation finished.");
    $finish(); 
end



endmodule

Step 2/hockey.vcd
$date
	Tue Jan 02 10:54:42 2024
$end
$version
	Icarus Verilog
$end
$timescale
	1s
$end
$scope module hockey_tb $end
$var wire 3 ! Y_COORD [2:0] $end
$var wire 3 " X_COORD [2:0] $end
$var parameter 64 # FP $end
$var parameter 32 $ HP $end
$var reg 1 % BTN_A $end
$var reg 1 & BTN_B $end
$var reg 2 ' DIR_A [1:0] $end
$var reg 2 ( DIR_B [1:0] $end
$var reg 3 ) Y_in_A [2:0] $end
$var reg 3 * Y_in_B [2:0] $end
$var reg 1 + clk $end
$var reg 1 , rst $end
$scope module dut $end
$var wire 1 % BTN_A $end
$var wire 1 & BTN_B $end
$var wire 2 - DIR_A [1:0] $end
$var wire 2 . DIR_B [1:0] $end
$var wire 3 / Y_in_A [2:0] $end
$var wire 3 0 Y_in_B [2:0] $end
$var wire 1 + clk $end
$var wire 1 , rst $end
$var parameter 4 1 DISPLAY $end
$var parameter 4 2 GAMEOVER $end
$var parameter 4 3 GOAL_A $end
$var parameter 4 4 GOAL_B $end
$var parameter 4 5 HIT_A $end
$var parameter 4 6 HIT_B $end
$var parameter 4 7 IDLE $end
$var parameter 4 8 RESP_A $end
$var parameter 4 9 RESP_B $end
$var parameter 4 : SEND_A $end
$var parameter 4 ; SEND_B $end
$var reg 3 < X_COORD [2:0] $end
$var reg 3 = Y_COORD [2:0] $end
$var reg 5 > currentstate [4:0] $end
$var reg 2 ? dir [1:0] $end
$var reg 2 @ lastTurn [1:0] $end
$var reg 3 A scoreA [2:0] $end
$var reg 3 B scoreB [2:0] $end
$var reg 8 C timer [7:0] $end
$var reg 1 D turn $end
$upscope $end
$upscope $end
$enddefinitions $end
$comment Show the parameter values. $end
$dumpall
b101 ;
b100 :
b111 9
b110 8
b0 7
b11 6
b10 5
b1001 4
b1000 3
b1010 2
b1 1
b101 $
b1010 #
$end
#0
$dumpvars
xD
b0 C
b0 B
b0 A
b0 @
bx ?
b0 >
b0 =
b0 <
b0 0
b0 /
b0 .
b0 -
1,
0+
b0 *
b0 )
b0 (
b0 '
0&
0%
b0 "
b0 !
$end
#5
1+
#10
0+
#15
1+
#20
0+
#25
1+
#30
0+
#35
1+
#40
0+
#45
1+
#50
0+
#55
1+
#60
0+
#65
1+
#70
0+
#75
1+
#80
0+
#85
1+
#90
0+
#95
1+
#100
0+
#105
1+
#110
0+
#115
1+
#120
0+
#125
1+
#130
0+
#135
1+
#140
0+
#145
1+
#150
0+
#155
1+
#160
0+
#165
1+
#170
0+
#175
1+
#180
0+
#185
1+
#190
0+
#195
1+
#200
0+
#205
1+
#210
0+
#215
1+
#220
0+
#225
1+
#230
0+
#235
1+
#240
0+
#245
1+
#250
0+
#255
1+
#260
0+
#265
1+
#270
0+
#275
1+
#280
0+
#285
1+
#290
0+
#295
1+
#300
0+
#305
1+
#310
0+
#315
1+
#320
0+
#325
1+
#330
0+
#335
1+
#340
0+
#345
1+
#350
0+
#355
1+
#360
0+
#365
1+
#370
0+
#375
1+
#380
0+
#385
1+
#390
0+
#395
1+
#400
0+
#405
1+
#410
0+
#415
1+
#420
0+
#425
1+
#430
0+
#435
1+
#440
0+
#445
1+
#450
0+
#455
1+
#460
0+
#465
1+
#470
0+
#475
1+
#480
0+
#485
1+
#490
0+
#495
1+
#500
0+
#505
1+
#510
0+
#515
1+
#520
0+
#525
1+
#530
0+
#535
1+
#540
0+
#545
1+
#550
0+
#555
1+
#560
0+
#565
1+
#570
0+
#575
1+
#580
0+
#585
1+
#590
0+
#595
1+
#600
0+
#605
1+
#610
0+
#615
1+
#620
0+
#625
1+
#630
0+
#635
1+
#640
0+
#645
1+
#650
0+
#655
1+
#660
0+
#665
1+
#670
0+
#675
1+
#680
0+
#685
1+
#690
0+
#695
1+
#700
0+
#705
1+
#710
0+
#715
1+
#720
0+
#725
1+
#730
0+
#735
1+
#740
0+
#745
1+
#750
0+
#755
1+
#760
0+
#765
1+
#770
0+
#775
1+
#780
0+
#785
1+
#790
0+
#795
1+
#800
0+
#805
1+
#810
0+
#815
1+
#820
0+
#825
1+
#830
0+
#835
1+
#840
0+
#845
1+
#850
0+
#855
1+
#860
0+
#865
1+
#870
0+
#875
1+
#880
0+
#885
1+
#890
0+
#895
1+
#900
0+
#905
1+
#910
0+
#915
1+
#920
0+
#925
1+
#930
0+
#935
1+
#940
0+
#945
1+
#950
0+
#955
1+
#960
0+
#965
1+
#970
0+
#975
1+
#980
0+
#985
1+
#990
0+
#995
1+
#1000
0+
#1005
1+
#1010
0+
#1015
1+
#1020
0+
#1025
1+
#1030
0+
#1035
1+
#1040
0+
#1045
1+
#1050
0+
#1055
1+
#1060
0+
#1065
1+
#1070
0+
#1075
1+
#1080
0+
#1085
1+
#1090
0+
#1095
1+
#1100
0+
#1105
1+
#1110
0+
#1115
1+
#1120
0+
#1125
1+
#1130
0+
#1135
1+
#1140
0+
#1145
1+
#1150
0+
#1155
1+
#1160
0+
#1165
1+
#1170
0+
#1175
1+
#1180
0+
#1185
1+
#1190
0+
#1195
1+
#1200
0+
#1205
1+
#1210
0+
#1215
1+
#1220
0+
#1225
1+
#1230
0+
#1235
1+
#1240
0+
#1245
1+
#1250
0+
#1255
1+
#1260
0+
#1265
1+
#1270
0+
#1275
1+
#1280
0+
#1285
1+
#1290
0+
#1295
1+
#1300
0+
#1305
1+
#1310
0+
#1315
1+
#1320
0+
#1325
1+
#1330
0+
#1335
1+
#1340
0+
#1345
1+
#1350
0+
#1355
1+
#1360
0+
#1365
1+
#1370
0+
#1375
1+
#1380
0+
#1385
1+
#1390
0+
#1395
1+
#1400
0+
#1405
1+
#1410
0+
#1415
1+
#1420
0+
#1425
1+
#1430
0+
#1435
1+
#1440
0+
#1445
1+
#1450
0+
#1455
1+
#1460
0+
#1465
1+
#1470
0+
#1475
1+
#1480
0+
#1485
1+
#1490
0+
#1495
1+
#1500
0+
#1505
1+
#1510
0+
#1515
1+
#1520
0+
#1525
1+
#1530
0+
#1535
1+
#1540
0+
#1545
1+
#1550
0+
#1555
1+
#1560
0+
#1565
1+
#1570
0+
#1575
1+
#1580
0+
#1585
1+
#1590
0+
#1595
1+
#1600
0+
#1605
1+
#1610
0+
#1615
1+
#1620
0+
#1625
1+
#1630
0+
#1635
1+
#1640
0+
#1645
1+
#1650
0+
#1655
1+
#1660
0+
#1665
1+
#1670
0+
#1675
1+
#1680
0+
#1685
1+
#1690
0+
#1695
1+
#1700
0+
#1705
1+
#1710
0+
#1715
1+
#1720
0+
#1725
1+
#1730
0+
#1735
1+
#1740
0+
#1745
1+
#1750
0+
#1755
1+
#1760
0+
#1765
1+
#1770
0+
#1775
1+
#1780
0+
#1785
1+
#1790
0+
#1795
1+
#1800
0+
#1805
1+
#1810
0+
#1815
1+
#1820
0+
#1825
1+
#1830
0+
#1835
1+
#1840
0+
#1845
1+
#1850
0+
#1855
1+
#1860
0+
#1865
1+
#1870
0+
#1875
1+
#1880
0+
#1885
1+
#1890
0+
#1895
1+
#1900
0+
#1905
1+
#1910
0+
#1915
1+
#1920
0+
#1925
1+
#1930
0+
#1935
1+
#1940
0+
#1945
1+
#1950
0+
#1955
1+
#1960
0+
#1965
1+
#1970
0+
#1975
1+
#1980
0+
#1985
1+
#1990
0+
#1995
1+
#2000
0+
1%
0,
#2005
b1 >
0D
1+
#2010
0+
#2015
b1 C
1+
#2020
0+
#2025
b10 C
1+
#2030
0+
#2035
b11 C
1+
#2040
0+
#2045
b100 C
1+
#2050
0+
#2055
b101 C
1+
#2060
0+
#2065
b110 C
1+
#2070
0+
#2075
b111 C
1+
#2080
0+
#2085
b1000 C
1+
#2090
0+
#2095
b1001 C
1+
#2100
0+
#2105
b1010 C
1+
#2110
0+
#2115
b1011 C
1+
#2120
0+
#2125
b1100 C
1+
#2130
0+
#2135
b1101 C
1+
#2140
0+
#2145
b1110 C
1+
#2150
0+
#2155
b1111 C
1+
#2160
0+
#2165
b10000 C
1+
#2170
0+
#2175
b10001 C
1+
#2180
0+
#2185
b10010 C
1+
#2190
0+
#2195
b10011 C
1+
#2200
0+
#2205
b10100 C
1+
#2210
0+
#2215
b10101 C
1+
#2220
0+
#2225
b10110 C
1+
#2230
0+
#2235
b10111 C
1+
#2240
0+
#2245
b11000 C
1+
#2250
0+
#2255
b11001 C
1+
#2260
0+
#2265
b11010 C
1+
#2270
0+
#2275
b11011 C
1+
#2280
0+
#2285
b11100 C
1+
#2290
0+
#2295
b11101 C
1+
#2300
0+
#2305
b11110 C
1+
#2310
0+
#2315
b11111 C
1+
#2320
0+
#2325
b100000 C
1+
#2330
0+
#2335
b100001 C
1+
#2340
0+
#2345
b100010 C
1+
#2350
0+
#2355
b100011 C
1+
#2360
0+
#2365
b100100 C
1+
#2370
0+
#2375
b100101 C
1+
#2380
0+
#2385
b100110 C
1+
#2390
0+
#2395
b100111 C
1+
#2400
0+
#2405
b101000 C
1+
#2410
0+
#2415
b101001 C
1+
#2420
0+
#2425
b101010 C
1+
#2430
0+
#2435
b101011 C
1+
#2440
0+
#2445
b101100 C
1+
#2450
0+
#2455
b101101 C
1+
#2460
0+
#2465
b101110 C
1+
#2470
0+
#2475
b101111 C
1+
#2480
0+
#2485
b110000 C
1+
#2490
0+
#2495
b110001 C
1+
#2500
0+
#2505
b110010 C
1+
#2510
0+
#2515
b110011 C
1+
#2520
0+
#2525
b110100 C
1+
#2530
0+
#2535
b110101 C
1+
#2540
0+
#2545
b110110 C
1+
#2550
0+
#2555
b110111 C
1+
#2560
0+
#2565
b111000 C
1+
#2570
0+
#2575
b111001 C
1+
#2580
0+
#2585
b111010 C
1+
#2590
0+
#2595
b111011 C
1+
#2600
0+
#2605
b111100 C
1+
#2610
0+
#2615
b111101 C
1+
#2620
0+
#2625
b111110 C
1+
#2630
0+
#2635
b111111 C
1+
#2640
0+
#2645
b1000000 C
1+
#2650
0+
#2655
b1000001 C
1+
#2660
0+
#2665
b1000010 C
1+
#2670
0+
#2675
b1000011 C
1+
#2680
0+
#2685
b1000100 C
1+
#2690
0+
#2695
b1000101 C
1+
#2700
0+
#2705
b1000110 C
1+
#2710
0+
#2715
b1000111 C
1+
#2720
0+
#2725
b1001000 C
1+
#2730
0+
#2735
b1001001 C
1+
#2740
0+
#2745
b1001010 C
1+
#2750
0+
#2755
b1001011 C
1+
#2760
0+
#2765
b1001100 C
1+
#2770
0+
#2775
b1001101 C
1+
#2780
0+
#2785
b1001110 C
1+
#2790
0+
#2795
b1001111 C
1+
#2800
0+
#2805
b1010000 C
1+
#2810
0+
#2815
b1010001 C
1+
#2820
0+
#2825
b1010010 C
1+
#2830
0+
#2835
b1010011 C
1+
#2840
0+
#2845
b1010100 C
1+
#2850
0+
#2855
b1010101 C
1+
#2860
0+
#2865
b1010110 C
1+
#2870
0+
#2875
b1010111 C
1+
#2880
0+
#2885
b1011000 C
1+
#2890
0+
#2895
b1011001 C
1+
#2900
0+
#2905
b1011010 C
1+
#2910
0+
#2915
b1011011 C
1+
#2920
0+
#2925
b1011100 C
1+
#2930
0+
#2935
b1011101 C
1+
#2940
0+
#2945
b1011110 C
1+
#2950
0+
#2955
b1011111 C
1+
#2960
0+
#2965
b1100000 C
1+
#2970
0+
#2975
b1100001 C
1+
#2980
0+
#2985
b1100010 C
1+
#2990
0+
#2995
b1100011 C
1+
#3000
0+
#3005
b1100100 C
1+
#3010
0+
#3015
b1100101 C
1+
#3020
0+
#3025
b1100110 C
1+
#3030
0+
#3035
b1100111 C
1+
#3040
0+
#3045
b1101000 C
1+
#3050
0+
#3055
b1101001 C
1+
#3060
0+
#3065
b1101010 C
1+
#3070
0+
#3075
b1101011 C
1+
#3080
0+
#3085
b1101100 C
1+
#3090
0+
#3095
b1101101 C
1+
#3100
0+
#3105
b1101110 C
1+
#3110
0+
#3115
b1101111 C
1+
#3120
0+
#3125
b1110000 C
1+
#3130
0+
#3135
b1110001 C
1+
#3140
0+
#3145
b1110010 C
1+
#3150
0+
#3155
b1110011 C
1+
#3160
0+
#3165
b1110100 C
1+
#3170
0+
#3175
b1110101 C
1+
#3180
0+
#3185
b1110110 C
1+
#3190
0+
#3195
b1110111 C
1+
#3200
0+
#3205
b1111000 C
1+
#3210
0+
#3215
b1111001 C
1+
#3220
0+
#3225
b1111010 C
1+
#3230
0+
#3235
b1111011 C
1+
#3240
0+
#3245
b1111100 C
1+
#3250
0+
#3255
b1111101 C
1+
#3260
0+
#3265
b1111110 C
1+
#3270
0+
#3275
b1111111 C
1+
#3280
0+
#3285
b10000000 C
1+
#3290
0+
#3295
b10000001 C
1+
#3300
0+
#3305
b10000010 C
1+
#3310
0+
#3315
b10000011 C
1+
#3320
0+
#3325
b10000100 C
1+
#3330
0+
#3335
b10000101 C
1+
#3340
0+
#3345
b10000110 C
1+
#3350
0+
#3355
b10000111 C
1+
#3360
0+
#3365
b10001000 C
1+
#3370
0+
#3375
b10001001 C
1+
#3380
0+
#3385
b10001010 C
1+
#3390
0+
#3395
b10001011 C
1+
#3400
0+
#3405
b10001100 C
1+
#3410
0+
#3415
b10001101 C
1+
#3420
0+
#3425
b10001110 C
1+
#3430
0+
#3435
b10001111 C
1+
#3440
0+
#3445
b10010000 C
1+
#3450
0+
#3455
b10010001 C
1+
#3460
0+
#3465
b10010010 C
1+
#3470
0+
#3475
b10010011 C
1+
#3480
0+
#3485
b10010100 C
1+
#3490
0+
#3495
b10010101 C
1+
#3500
0+
#3505
b10010110 C
1+
#3510
0+
#3515
b10010111 C
1+
#3520
0+
#3525
b10011000 C
1+
#3530
0+
#3535
b10011001 C
1+
#3540
0+
#3545
b10011010 C
1+
#3550
0+
#3555
b10011011 C
1+
#3560
0+
#3565
b10011100 C
1+
#3570
0+
#3575
b10011101 C
1+
#3580
0+
#3585
b10011110 C
1+
#3590
0+
#3595
b10011111 C
1+
#3600
0+
#3605
b10100000 C
1+
#3610
0+
#3615
b10100001 C
1+
#3620
0+
#3625
b10100010 C
1+
#3630
0+
#3635
b10100011 C
1+
#3640
0+
#3645
b10100100 C
1+
#3650
0+
#3655
b10100101 C
1+
#3660
0+
#3665
b10100110 C
1+
#3670
0+
#3675
b10100111 C
1+
#3680
0+
#3685
b10101000 C
1+
#3690
0+
#3695
b10101001 C
1+
#3700
0+
#3705
b10101010 C
1+
#3710
0+
#3715
b10101011 C
1+
#3720
0+
#3725
b10101100 C
1+
#3730
0+
#3735
b10101101 C
1+
#3740
0+
#3745
b10101110 C
1+
#3750
0+
#3755
b10101111 C
1+
#3760
0+
#3765
b10110000 C
1+
#3770
0+
#3775
b10110001 C
1+
#3780
0+
#3785
b10110010 C
1+
#3790
0+
#3795
b10110011 C
1+
#3800
0+
#3805
b10110100 C
1+
#3810
0+
#3815
b10110101 C
1+
#3820
0+
#3825
b10110110 C
1+
#3830
0+
#3835
b10110111 C
1+
#3840
0+
#3845
b10111000 C
1+
#3850
0+
#3855
b10111001 C
1+
#3860
0+
#3865
b10111010 C
1+
#3870
0+
#3875
b10111011 C
1+
#3880
0+
#3885
b10111100 C
1+
#3890
0+
#3895
b10111101 C
1+
#3900
0+
#3905
b10111110 C
1+
#3910
0+
#3915
b10111111 C
1+
#3920
0+
#3925
b11000000 C
1+
#3930
0+
#3935
b11000001 C
1+
#3940
0+
#3945
b11000010 C
1+
#3950
0+
#3955
b11000011 C
1+
#3960
0+
#3965
b11000100 C
1+
#3970
0+
#3975
b11000101 C
1+
#3980
0+
#3985
b11000110 C
1+
#3990
0+
#3995
b11000111 C
1+
#4000
0+
0%
#4005
b10 >
b0 C
1+
